hatch_pyside/__about__.py
hatch_pyside/__init__.py
hatch_pyside/__main__.py
hatch_pyside/build.py
hatch_pyside/config.py
hatch_pyside/gui/__init__.py
hatch_pyside/gui/about.ui
hatch_pyside/gui/app.py
hatch_pyside/gui/hatch-pyside.pyproject
hatch_pyside/gui/mainwindow.py
hatch_pyside/gui/mainwindow.ui
hatch_pyside/gui/project_chooser_dlg.ui
hatch_pyside/gui/ui_about.py
hatch_pyside/gui/ui_mainwindow.py
hatch_pyside/gui/ui_project_chooser_dlg.py
hatch_pyside/plugin/__init__.py
hatch_pyside/plugin/hooks.py
hatch_pyside/plugin/plugin.py
hatch_pyside-0.5.5.dist-info/METADATA
hatch_pyside-0.5.5.dist-info/WHEEL
hatch_pyside-0.5.5.dist-info/entry_points.txt
hatch_pyside-0.5.5.dist-info/licenses/LICENSE.txt
hatch_pyside-0.5.5.dist-info/RECORD
