Metadata-Version: 2.4
Name: hatch-pyside
Version: 0.5.5
Summary: A hatch plugin to build Pyside6 elements
Project-URL: Documentation, https://github.com/s-ball/hatch-pyside#readme
Project-URL: Issues, https://github.com/s-ball/hatch-pyside/issues
Project-URL: Source, https://github.com/s-ball/hatch-pyside
Author-email: s-ball <s-ball@laposte.net>
License-Expression: MIT
License-File: LICENSE.txt
Classifier: Development Status :: 4 - Beta
Classifier: Framework :: Hatch
Classifier: Programming Language :: Python
Classifier: Programming Language :: Python :: 3.9
Classifier: Programming Language :: Python :: 3.10
Classifier: Programming Language :: Python :: 3.11
Classifier: Programming Language :: Python :: 3.12
Classifier: Programming Language :: Python :: 3.13
Classifier: Programming Language :: Python :: Implementation :: CPython
Requires-Python: >=3.9
Requires-Dist: pyside6==6.8.*
Requires-Dist: tomli; python_version < '3.11'
